{
  "project_info": {
    "project_number": "1028649221876",
    "firebase_url": "https://time-capsule-8b48f.firebaseio.com",
    "project_id": "time-capsule-8b48f",
    "storage_bucket": "time-capsule-8b48f.appspot.com"
  },
  "client": [
    {
      "client_info": {
        "mobilesdk_app_id": "1:1028649221876:android:c41583df871ad236",
        "android_client_info": {
          "package_name": "com.android121.timecapsule"
        }
      },
      "oauth_client": [
        {
          "client_id": "1028649221876-8pceobvvtartctrele8r8kcabv1tcaj8.apps.googleusercontent.com",
          "client_type": 1,
          "android_info": {
            "package_name": "com.android121.timecapsule",
            "certificate_hash": "0527d86f1dac7c4e50ed72a392902432adcb4711"
          }
        },
        {
          "client_id": "1028649221876-3r0kso2h1d13se2nsfrhncqp8v3et3h2.apps.googleusercontent.com",
          "client_type": 3
        }
      ],
      "api_key": [
        {
          "current_key": "AIzaSyBwL4R0WoMJa14tLqrV-zvTqPqJlj00_00"
        }
      ],
      "services": {
        "appinvite_service": {
          "other_platform_oauth_client": [
            {
              "client_id": "1028649221876-3r0kso2h1d13se2nsfrhncqp8v3et3h2.apps.googleusercontent.com",
              "client_type": 3
            }
          ]
        }
      }
    }
  ],
  "configuration_version": "1"
}